ezbilling/__init__.py
ezbilling/payment_gateway.py
ezbilling-0.5.0.dist-info/licenses/LICENSE
ezbilling-0.5.0.dist-info/METADATA
ezbilling-0.5.0.dist-info/WHEEL
ezbilling-0.5.0.dist-info/top_level.txt
ezbilling-0.5.0.dist-info/RECORD
