Metadata-Version: 2.4
Name: ezbilling
Version: 0.5.0
Summary: A small Python package that says hello.
Home-page: https://github.com/Ezbillpay
Author: Nithesh
Author-email: Nithesh <nithish@dreaminfinity.in>
License: MIT
Classifier: Programming Language :: Python :: 3
Classifier: License :: OSI Approved :: MIT License
Classifier: Operating System :: OS Independent
Requires-Python: >=3.7
License-File: LICENSE
Requires-Dist: requests>=2.25.1
Dynamic: author
Dynamic: home-page
Dynamic: license-file
Dynamic: requires-python
